{
  "recipe": [
    {
      "id": 1,
      "recipeName": "チキンソテーのトマトソース掛け",
      "userName": "ユーザーネームユーザーネーム",
      "cookingTime": "30分",
      "recipeMaterial": "鶏胸肉",
      "recipeQuantity": "2枚",
      "recipeHowToMake": "１番目の作り方１番目の作り方１番目の作り方１番目の作り方１番目の作り方１番目の作り方"
    },
    {
      "id": 1,
      "recipeName": "チキンソテーのトマトソース掛け",
      "userName": "ユーザーネームユーザーネーム",
      "cookingTime": "30分",
      "recipeMaterial": "鶏胸肉",
      "recipeQuantity": "2枚",
      "recipeHowToMake": "１番目の作り方１番目の作り方１番目の作り方１番目の作り方１番目の作り方１番目の作り方"
    }
  ],
  "vegetable": [
    {
      "id": 1,
      "materialName": "レタス",
      "materialImageUrl": "/public/materialImage/retasu.png"
    }
  ]
}
